CHANGES.rst
MANIFEST.in
README.rst
setup.cfg
setup.py
Solgema/__init__.py
Solgema.RichMenu.egg-info/PKG-INFO
Solgema.RichMenu.egg-info/SOURCES.txt
Solgema.RichMenu.egg-info/dependency_links.txt
Solgema.RichMenu.egg-info/entry_points.txt
Solgema.RichMenu.egg-info/namespace_packages.txt
Solgema.RichMenu.egg-info/not-zip-safe
Solgema.RichMenu.egg-info/requires.txt
Solgema.RichMenu.egg-info/top_level.txt
Solgema/RichMenu/__init__.py
Solgema/RichMenu/catalog.py
Solgema/RichMenu/catalog.zcml
Solgema/RichMenu/config.py
Solgema/RichMenu/configure.zcml
Solgema/RichMenu/interfaces.py
Solgema/RichMenu/profiles.zcml
Solgema/RichMenu/setuphandlers.py
Solgema/RichMenu/versions.txt
Solgema/RichMenu/browser/__init__.py
Solgema/RichMenu/browser/configure.zcml
Solgema/RichMenu/browser/content.py
Solgema/RichMenu/browser/navigation.py
Solgema/RichMenu/browser/p4_controlanel.zcml
Solgema/RichMenu/browser/p4_controlpanel.zcml
Solgema/RichMenu/dx/__init__.py
Solgema/RichMenu/dx/configure.zcml
Solgema/RichMenu/dx/content.py
Solgema/RichMenu/dx/interfaces.py
Solgema/RichMenu/dx/migration.py
Solgema/RichMenu/dx/navigation.py
Solgema/RichMenu/dx/richmenu_view_item.pt
Solgema/RichMenu/locales/Solgema.RichMenu.pot
Solgema/RichMenu/locales/update.sh
Solgema/RichMenu/locales/de/LC_MESSAGES/Solgema.RichMenu.mo
Solgema/RichMenu/locales/de/LC_MESSAGES/Solgema.RichMenu.po
Solgema/RichMenu/locales/en/LC_MESSAGES/Solgema.RichMenu.mo
Solgema/RichMenu/locales/en/LC_MESSAGES/Solgema.RichMenu.po
Solgema/RichMenu/locales/fr/LC_MESSAGES/Solgema.RichMenu.mo
Solgema/RichMenu/locales/fr/LC_MESSAGES/Solgema.RichMenu.po
Solgema/RichMenu/locales/it/LC_MESSAGES/Solgema.RichMenu.mo
Solgema/RichMenu/locales/it/LC_MESSAGES/Solgema.RichMenu.po
Solgema/RichMenu/locales/no/LC_MESSAGES/Solgema.RichMenu.mo
Solgema/RichMenu/locales/no/LC_MESSAGES/Solgema.RichMenu.po
Solgema/RichMenu/profiles/default/actions.xml
Solgema/RichMenu/profiles/default/browserlayer.xml
Solgema/RichMenu/profiles/default/catalog.xml
Solgema/RichMenu/profiles/default/controlpanel.xml
Solgema/RichMenu/profiles/default/import_steps.xml
Solgema/RichMenu/profiles/default/metadata.xml
Solgema/RichMenu/profiles/default/skins.xml
Solgema/RichMenu/profiles/default/solgema_richmenu.txt
Solgema/RichMenu/profiles/default/viewlets.xml
Solgema/RichMenu/profiles/plone4/controlpanel.xml
