Metadata-Version: 1.1
Name: Solgema.RichMenu
Version: 1.6.6
Summary: Solgema RichMenu for Plone
Home-page: http://www.martronic.ch/plone_products/Solgema.RichMenu
Author: Martronic SA
Author-email: martronic@martronic.ch
License: GPL
Keywords: Solgema
Platform: UNKNOWN
Classifier: Framework :: Plone
Classifier: Programming Language :: Python
Classifier: Topic :: Software Development :: Libraries :: Python Modules
